{"sweets": {"available": "10a-4p", "items": [{"id": "0001", "type": "donut hole", "name": "anti-cake", "price": 4.95, "ingredients": {"batter": [{"id": "1001", "type": "Regular", "add": 0}, {"id": "1003", "type": "Blueberry", "add": 0.5}, {"id": "1006", "type": "Caramel", "add": 0.5}, {"id": "1007", "type": "Mulberry", "add": 0.5}, {"id": "1008", "type": "Angel's Food", "add": 0.75}, {"id": "1009", "type": "Fudge", "add": 0.75}, {"id": "1010", "type": "Strawberry", "add": 0.5}, {"id": "1011", "type": "Diet", "add": 0.5}], "topping": [{"id": "3001", "type": "None", "add": 0}, {"id": "3002", "type": "Glazed", "add": 0.5}, {"id": "3003", "type": "Sugar", "add": 0.25}, {"id": "3005", "type": "Cinnamon Sugar", "add": 0.5}, {"id": "3006", "type": "Sea Salt", "add": 0.25}, {"id": "3008", "type": "Chocolate with Sprinkles", "add": 0.75}, {"id": "3009", "type": "Chocolate", "add": 0.5}, {"id": "3010", "type": "M and M", "add": 0.5}, {"id": "3011", "type": "Sour kids", "add": 0.5}, {"id": "3012", "type": "Oreo", "add": 0.5}, {"id": "3013", "type": "Nutella", "add": 0.5}]}}, {"id": "0002", "type": "fried donut", "name": "unicorn butt sneeze", "price": 5.95, "ingredients": {"batter": [{"id": "1001", "type": "Regular", "add": 0}, {"id": "1002", "type": "Chocolate", "add": 0.5}, {"id": "1003", "type": "Blueberry", "add": 0.5}, {"id": "1004", "type": "Devil's Food", "add": 0.5}, {"id": "1005", "type": "Sour", "add": 0.5}, {"id": "1006", "type": "Caramel", "add": 0.5}, {"id": "1007", "type": "Mulberry", "add": 0.5}, {"id": "1009", "type": "Fudge", "add": 0.75}, {"id": "1010", "type": "Strawberry", "add": 0.5}], "topping": [{"id": "3001", "type": "None", "add": 0}, {"id": "3002", "type": "Glazed", "add": 0.5}, {"id": "3003", "type": "Sugar", "add": 0.25}, {"id": "3004", "type": "Powdered Sugar", "add": 0.5}, {"id": "3005", "type": "Cinnamon Sugar", "add": 0.5}, {"id": "3008", "type": "Chocolate with Sprinkles", "add": 0.75}, {"id": "3009", "type": "Chocolate", "add": 0.5}, {"id": "3010", "type": "M and M", "add": 0.5}, {"id": "3011", "type": "Sour kids", "add": 0.5}, {"id": "3013", "type": "Nutella", "add": 0.5}, {"id": "3014", "type": "Maple", "add": 0.75}, {"id": "3015", "type": "Special", "add": 1.25}]}}, {"id": "0003", "type": "bagel", "name": "einstein", "price": 3.95, "ingredients": {"batter": [{"id": "1001", "type": "Regular", "add": 0}, {"id": "1003", "type": "Blueberry", "add": 0.5}, {"id": "1004", "type": "Devil's Food", "add": 0.5}, {"id": "1005", "type": "Sour", "add": 0.5}, {"id": "1006", "type": "Caramel", "add": 0.5}, {"id": "1007", "type": "Mulberry", "add": 0.5}, {"id": "1008", "type": "Angel's Food", "add": 0.75}, {"id": "1010", "type": "Strawberry", "add": 0.5}, {"id": "1011", "type": "Diet", "add": 0.5}], "topping": [{"id": "3001", "type": "None", "add": 0}, {"id": "3005", "type": "Cinnamon Sugar", "add": 0.5}, {"id": "3006", "type": "Sea Salt", "add": 0.25}, {"id": "3007", "type": "Old Bay", "add": 0.5}, {"id": "3008", "type": "Chocolate with Sprinkles", "add": 0.75}, {"id": "3009", "type": "Chocolate", "add": 0.5}, {"id": "3010", "type": "M and M", "add": 0.5}, {"id": "3012", "type": "Oreo", "add": 0.5}, {"id": "3013", "type": "Nutella", "add": 0.5}, {"id": "3014", "type": "Maple", "add": 0.75}]}}]}, "beverages": {"available": "8a-10p", "items": [{"id": "2001", "type": "coffee", "name": "irish", "price": 8.95, "ingredients": {"base": [{"id": "5001", "type": "Regular", "add": 0}, {"id": "5002", "type": "Decaf", "add": 0.95}, {"id": "5003", "type": "Double", "add": 0.95}], "condiment": [{"id": "7001", "type": "None", "add": 0}, {"id": "7002", "type": "Cream", "add": 0.25}, {"id": "7003", "type": "Sugar", "add": 0}, {"id": "7004", "type": "Almond milk", "add": 0.75}, {"id": "7005", "type": "Soy milk", "add": 0.75}]}}, {"id": "2002", "type": "capucino", "name": "Fusion", "price": 6.95, "ingredients": {"base": [{"id": "5001", "type": "Regular", "add": 0}, {"id": "5002", "type": "Double shot", "add": 0.75}, {"id": "5003", "type": "Triple shot", "add": 1.5}], "condiment": [{"id": "7001", "type": "None", "add": 0}, {"id": "7002", "type": "Cream", "add": 0.25}, {"id": "7003", "type": "Sugar", "add": 0}, {"id": "7004", "type": "Almond milk", "add": 0.75}, {"id": "7005", "type": "Soy milk", "add": 0.75}]}}]}}